rsp/__init__.py
rsp/rsp_tokenizer.py
rsp/util.py
rsp/bert-base-multilingual-cased/tokenizer.json
rsp/bert-base-multilingual-cased/tokenizer_config.json
rsp/bert-base-multilingual-cased/vocab.txt
rsp_alamo-1.0.8.dist-info/LICENSE
rsp_alamo-1.0.8.dist-info/METADATA
rsp_alamo-1.0.8.dist-info/WHEEL
rsp_alamo-1.0.8.dist-info/top_level.txt
rsp_alamo-1.0.8.dist-info/RECORD
