Metadata-Version: 2.1
Name: rsp-alamo
Version: 1.0.8
Summary: Python extension for processing random string
Home-page: https://gitee.com/alamoliuyang/rsp
Author: alamo
Author-email: 453638071@qq.com
License: MIT License
Platform: all
Classifier: Intended Audience :: Developers
Classifier: Operating System :: OS Independent
Classifier: Natural Language :: Chinese (Simplified)
Classifier: Programming Language :: Python :: 3
Classifier: Programming Language :: Python :: 3.8
Classifier: Topic :: Software Development :: Libraries
License-File: LICENSE
Requires-Dist: transformers ==4.33.1
